cppfingercount/__init__.py
cppfingercount/cppfingercount.py
cppfingercount-0.0.5.dist-info/METADATA
cppfingercount-0.0.5.dist-info/WHEEL
cppfingercount-0.0.5.dist-info/top_level.txt
cppfingercount-0.0.5.dist-info/RECORD
