Metadata-Version: 2.1
Name: cppfingercount
Version: 0.0.5
Summary: Made by x21223572. cpp-project finger count package 
Home-page: UNKNOWN
Author: harsh mall
Author-email: contact.harshmall@gmail.com
License: UNKNOWN
Keywords: python,video,camera,base64,finger count,number
Platform: UNKNOWN
Classifier: Development Status :: 1 - Planning
Classifier: Intended Audience :: Developers
Classifier: Programming Language :: Python :: 3
Classifier: Operating System :: Unix
Classifier: Operating System :: MacOS :: MacOS X
Classifier: Operating System :: Microsoft :: Windows
Requires-Dist: opencv-python
Requires-Dist: mediapipe
Requires-Dist: numpy
